ucamvrobillpsql/DBA.py
ucamvrobillpsql/__init__.py
ucamvrobillpsql/__main__.py
ucamvrobillpsql/ca.crt
ucamvrobillpsql/exceptions.py
ucamvrobillpsql/tests/__init__.py
ucamvrobillpsql/tests/conftest.py
ucamvrobillpsql/tests/dbconnect.py
ucamvrobillpsql/tests/test_DB.py
ucamvrobillpsql/tests/utils.py
ucamvrobillpsql/tools.py
ucamvrobillpsql/utils.py
ucamvrobillpsql-0.1.0.dist-info/LICENSE
ucamvrobillpsql-0.1.0.dist-info/METADATA
ucamvrobillpsql-0.1.0.dist-info/WHEEL
ucamvrobillpsql-0.1.0.dist-info/RECORD
