Metadata-Version: 2.3
Name: ucamvrobillpsql
Version: 0.1.0
Summary: MOA DB connection for billing.
License: MIT
Author: Ishan Mahajan
Author-email: mahanishanmahajan@gmail.com
Requires-Python: >=3.10
Classifier: License :: OSI Approved :: MIT License
Classifier: Programming Language :: Python :: 3
Classifier: Programming Language :: Python :: 3.10
Classifier: Programming Language :: Python :: 3.11
Classifier: Programming Language :: Python :: 3.12
Classifier: Programming Language :: Python :: 3.13
Requires-Dist: psycopg2-binary (>=2.9.10,<3.0.0)
